README.rst
setup.py
bin/cumulus
cumulus/CFStack.py
cumulus/MegaStack.py
cumulus/__init__.py
cumulus_aws.egg-info/PKG-INFO
cumulus_aws.egg-info/SOURCES.txt
cumulus_aws.egg-info/dependency_links.txt
cumulus_aws.egg-info/entry_points.txt
cumulus_aws.egg-info/requires.txt
cumulus_aws.egg-info/top_level.txt