Metadata-Version: 1.1
Name: cumulus-aws
Version: 1.0.0
Summary: Manages AWS Cloudformation stacks across multiple CF templates
Home-page: https://github.com/cotdsa/cumulus
Author: Peter Hall
Author-email: cumulus@peterkh.net
License: Apache Software License 2.0
Platform: UNKNOWN
Classifier: Development Status :: 5 - Production/Stable
Classifier: Intended Audience :: System Administrators
Classifier: Topic :: System :: Systems Administration
Classifier: License :: OSI Approved :: MIT License
Classifier: Programming Language :: Python :: 2.7
